design.v
module AWMC(input clk,  
                  reset,
                  start,
                  pause,
            output reg [2:0] stage,
            output reg done);

    parameter IDLE  = 3'b111,
              FILL  = 3'b000,
              WASH  = 3'b001,
              RINSE = 3'b010,
              SPIN  = 3'b011,
              STOP  = 3'b100,
              TIMER = 4'd10,
              VALVE_DURATION = 2'd2;


    reg [2:0] prev_state;
    reg [3:0] count;
    reg input_valve;
    reg output_drain;
    reg running;
    reg paused;

    always @(posedge clk or posedge reset) begin
        if(reset) begin
            count <= 2'b00;
            case (stage)
                WASH : begin
                    if(input_valve == 1'b1) begin
                        input_valve <= 1'b0;
                        if(count < VALVE_DURATION) begin
                                output_drain <= 1'b1;
                                count++;
                        end
                        else begin
                                output_drain <= 1'b0;
                                count <= 2'b00;
                        end
                    end
                    else begin
                        input_valve <= 1'b0;
                        output_drain <= 1'b0;
                    end
                end
                RINSE : begin
                    if(input_valve == 1'b1 || output_drain == 1'b1) begin
                        input_valve <= 1'b0;
                        if(count < VALVE_DURATION) begin
                                output_drain <= 1'b1;
                                count++;
                        end
                        else begin
                                output_drain <= 1'b0;
                                count <= 2'b00;
                        end
                    end
                end
                SPIN : begin
                    if(output_drain == 1'b1) begin
                        if(count < VALVE_DURATION) begin
                                output_drain <= 1'b1;
                                count++;
                        end
                        else begin
                                output_drain <= 1'b0;
                                count <= 2'b00;
                        end
                    end
                end
                default : begin
                    input_valve <= 1'b0;
                    output_drain <= 1'b0;
                end
            endcase

        stage <= IDLE;
        prev_state <= IDLE;
        running <= 1'b0;
        paused <= 1'b0;
        done <= 1'b0;
            
        end
        else begin
            if(pause) begin
                running <= 1'b0;
                if(stage != IDLE) 
                    prev_state <= stage;
                stage <= IDLE;
                paused <= 1'b1;
                input_valve <= 1'b0;
                output_drain <= 1'b0;
            end
            else if(start || ((running || paused) && !done)) begin
                running <= 1'b1;
                if(paused) begin
                    stage <= prev_state;
                    paused <= 1'b0;
                end

                case (stage)
                    FILL: begin
                          input_valve <= 1'b0;
                          output_drain <= 1'b0;
                    end
                    WASH: begin
                        output_drain <= 1'b0;
                        if(count < VALVE_DURATION)
                            input_valve <= 1'b1;
                        else
                            input_valve <= 1'b0;       
                    end
                    RINSE: begin
                            case (count) 
                                4'd0: begin input_valve <= 1'b0 ; output_drain <= 1'b1; end
                                4'd2: begin input_valve <= 1'b1 ; output_drain <= 1'b0; end
                                4'd4: begin input_valve <= 1'b0 ; output_drain <= 1'b1; end
                                4'd6: begin input_valve <= 1'b1 ; output_drain <= 1'b0; end
                                4'd8: begin input_valve <= 1'b0 ; output_drain <= 1'b1; end
                                4'd10:begin input_valve <= 1'b0 ; output_drain <= 1'b1; end
                            endcase
                    end
                    SPIN: begin
                        input_valve <= 1'b0;
                        if(count < VALVE_DURATION)
                            output_drain <= 1'b1;
                        else
                            output_drain <= 1'b0;
                    end
                endcase                
                if(count < TIMER) begin
                    count <= count + 1;
                end
                else begin
                    if (stage == STOP) begin
                        done <= 1'b1;
                        running <= 1'b0;
                        stage <= IDLE;
                        count <= 2'b00;
                    end
                    else begin
                        stage <= stage + 1;
                        done <= 1'b0;
                        count <= 2'b00;
                    end
                end
            end 
        end
    end
endmodule

tb.v
`include "design.v"

module AWMC_tb();
    reg clk, reset, start, pause;
    wire [2:0] stage;
    wire done;

    AWMC uut(.clk(clk),.reset(reset),.start(start),.pause(pause),.stage(stage),.done(done));

    initial begin
        reset = 1'b0;
        #1
        reset = 1'b1;
        #1
        reset = 1'b0;
        clk = 1'b0;

        forever #5 clk = ~clk;
    end

    initial begin
        start = 1'b0;
        pause = 1'b0;

        $dumpfile("tb.vcd");
        $dumpvars(0,AWMC_tb);

        #10
        start = 1'b1;
        #20
        start = 1'b0;
        #100
        pause = 1'b1;
        #105
        pause = 1'b0;
        #110
        start = 1'b1;
        #120 
        start = 1'b0;
        #135
        reset = 1'b1;
        #150
        reset = 1'b0;
        #155
        start = 1'b1;
        #160
        start = 1'b0;
        #165
        pause = 1'b1;
        #170
        pause = 1'b0;
        #200
        reset = 1'b1;
        #205
        reset = 1'b0;  

        #300 $finish;

    end

endmodule

tb.vcd
$date
	Mon Aug  4 09:48:17 2025
$end
$version
	Icarus Verilog
$end
$timescale
	1s
$end
$scope module AWMC_tb $end
$var wire 3 ! stage [2:0] $end
$var wire 1 " done $end
$var reg 1 # clk $end
$var reg 1 $ pause $end
$var reg 1 % reset $end
$var reg 1 & start $end
$scope module uut $end
$var wire 1 # clk $end
$var wire 1 $ pause $end
$var wire 1 % reset $end
$var wire 1 & start $end
$var reg 4 ' count [3:0] $end
$var reg 1 " done $end
$var reg 1 ( input_valve $end
$var reg 1 ) output_drain $end
$var reg 1 * paused $end
$var reg 3 + prev_state [2:0] $end
$var reg 1 , running $end
$var reg 3 - stage [2:0] $end
$upscope $end
$upscope $end
$enddefinitions $end
#0
$dumpvars
bx -
x,
bx +
x*
x)
x(
bx '
0&
0%
0$
x#
x"
bx !
$end
#1
0"
0*
0,
b111 +
b111 !
b111 -
0)
0(
b0 '
1%
#2
0#
0%
#7
1#
#10
1&
#12
0#
#17
b1 '
1,
1#
#22
0#
#27
b10 '
1#
#30
0&
#32
0#
#37
b11 '
1#
#42
0#
#47
b100 '
1#
#52
0#
#57
b101 '
1#
#62
0#
#67
b110 '
1#
#72
0#
#77
b111 '
1#
#82
0#
#87
b1000 '
1#
#92
0#
#97
b1001 '
1#
#102
0#
#107
b1010 '
1#
#112
0#
#117
b0 '
b0 !
b0 -
1#
#122
0#
#127
b1 '
1#
#130
1$
#132
0#
#137
1*
b111 !
b111 -
b0 +
0,
1#
#142
0#
#147
1#
#152
0#
#157
1#
#162
0#
#167
1#
#172
0#
#177
1#
#182
0#
#187
1#
#192
0#
#197
1#
#202
0#
#207
1#
#212
0#
#217
1#
#222
0#
#227
1#
#232
0#
#235
0$
#237
b10 '
0*
b0 !
b0 -
1,
1#
#242
0#
#247
b11 '
1#
#252
0#
#257
b100 '
1#
#262
0#
#267
b101 '
1#
#272
0#
#277
b110 '
1#
#282
0#
#287
b111 '
1#
#292
0#
#297
b1000 '
1#
#302
0#
#307
b1001 '
1#
#312
0#
#317
b1010 '
1#
#322
0#
#327
b0 '
b1 !
b1 -
1#
#332
0#
#337
b1 '
1(
1#
#342
0#
#345
1&
#347
b10 '
1#
#352
0#
#357
b11 '
0(
1#
#362
0#
#367
b100 '
1#
#372
0#
#377
b101 '
1#
#382
0#
#387
b110 '
1#
#392
0#
#397
b111 '
1#
#402
0#
#407
b1000 '
1#
#412
0#
#417
b1001 '
1#
#422
0#
#427
b1010 '
1#
#432
0#
#437
b0 '
b10 !
b10 -
1#
#442
0#
#447
b1 '
1)
1#
#452
0#
#457
b10 '
1#
#462
0#
#465
0&
#467
b11 '
0)
1(
1#
#472
0#
#477
b100 '
1#
#482
0#
#487
b101 '
1)
0(
1#
#492
0#
#497
b110 '
1#
#502
0#
#507
b111 '
0)
1(
1#
#512
0#
#517
b1000 '
1#
#522
0#
#527
b1001 '
1)
0(
1#
#532
0#
#537
b1010 '
1#
#542
0#
#547
b0 '
b11 !
b11 -
1#
#552
0#
#557
b1 '
1#
#562
0#
#567
b10 '
1#
#572
0#
#577
b11 '
0)
1#
#582
0#
#587
b100 '
1#
#592
0#
#597
b101 '
1#
#600
0,
b111 +
b111 !
b111 -
b0 '
1%
#602
0#
#607
1#
#612
0#
#617
1#
#622
0#
#627
1#
#632
0#
#637
1#
#642
0#
#647
1#
#652
0#
#657
1#
#662
0#
#667
1#
#672
0#
#677
1#
#682
0#
#687
1#
#692
0#
#697
1#
#702
0#
#707
1#
#712
0#
#717
1#
#722
0#
#727
1#
#732
0#
#737
1#
#742
0#
#747
1#
#750
0%
#752
0#
#757
1#
#762
0#
#767
1#
#772
0#
#777
1#
#782
0#
#787
1#
#792
0#
#797
1#
#802
0#
#807
1#
#812
0#
#817
1#
#822
0#
#827
1#
#832
0#
#837
1#
#842
0#
#847
1#
#852
0#
#857
1#
#862
0#
#867
1#
#872
0#
#877
1#
#882
0#
#887
1#
#892
0#
#897
1#
#902
0#
#905
1&
#907
b1 '
1,
1#
#912
0#
#917
b10 '
1#
#922
0#
#927
b11 '
1#
#932
0#
#937
b100 '
1#
#942
0#
#947
b101 '
1#
#952
0#
#957
b110 '
1#
#962
0#
#967
b111 '
1#
#972
0#
#977
b1000 '
1#
#982
0#
#987
b1001 '
1#
#992
0#
#997
b1010 '
1#
#1002
0#
#1007
b0 '
b0 !
b0 -
1#
#1012
0#
#1017
b1 '
1#
#1022
0#
#1027
b10 '
1#
#1032
0#
#1037
b11 '
1#
#1042
0#
#1047
b100 '
1#
#1052
0#
#1057
b101 '
1#
#1062
0#
#1065
0&
#1067
b110 '
1#
#1072
0#
#1077
b111 '
1#
#1082
0#
#1087
b1000 '
1#
#1092
0#
#1097
b1001 '
1#
#1102
0#
#1107
b1010 '
1#
#1112
0#
#1117
b0 '
b1 !
b1 -
1#
#1122
0#
#1127
b1 '
1(
1#
#1132
0#
#1137
b10 '
1#
#1142
0#
#1147
b11 '
0(
1#
#1152
0#
#1157
b100 '
1#
#1162
0#
#1167
b101 '
1#
#1172
0#
#1177
b110 '
1#
#1182
0#
#1187
b111 '
1#
#1192
0#
#1197
b1000 '
1#
#1202
0#
#1207
b1001 '
1#
#1212
0#
#1217
b1010 '
1#
#1222
0#
#1227
b0 '
b10 !
b10 -
1#
#1230
1$
#1232
0#
#1237
1*
b111 !
b111 -
b10 +
0,
1#
#1242
0#
#1247
1#
#1252
0#
#1257
1#
#1262
0#
#1267
1#
#1272
0#
#1277
1#
#1282
0#
#1287
1#
#1292
0#
#1297
1#
#1302
0#
#1307
1#
#1312
0#
#1317
1#
#1322
0#
#1327
1#
#1332
0#
#1337
1#
#1342
0#
#1347
1#
#1352
0#
#1357
1#
#1362
0#
#1367
1#
#1372
0#
#1377
1#
#1382
0#
#1387
1#
#1392
0#
#1397
1#
#1400
0$
#1402
0#
#1407
b1 '
0*
b10 !
b10 -
1,
1#
#1412
0#
#1417
b10 '
1#
#1422
0#
#1427
b11 '
1(
1#
#1432
0#
#1437
b100 '
1#
#1442
0#
#1447
b101 '
1)
0(
1#
#1452
0#
#1457
b110 '
1#
#1462
0#
#1467
b111 '
0)
1(
1#
#1472
0#
#1477
b1000 '
1#
#1482
0#
#1487
b1001 '
1)
0(
1#
#1492
0#
#1497
b1010 '
1#
#1502
0#
#1507
b0 '
b11 !
b11 -
1#
#1512
0#
#1517
b1 '
1#
#1522
0#
#1527
b10 '
1#
#1532
0#
#1537
b11 '
0)
1#
#1542
0#
#1547
b100 '
1#
#1552
0#
#1557
b101 '
1#
#1562
0#
#1567
b110 '
1#
#1572
0#
#1577
b111 '
1#
#1582
0#
#1587
b1000 '
1#
#1592
0#
#1597
b1001 '
1#
#1600
0,
b111 +
b111 !
b111 -
b0 '
1%
