design.v
module AWMC(input clk,  
                  reset,
                  start,
                  pause,
                  lid,
            output reg [2:0] stage,
            output reg done,
            output reg input_valve,
            output reg output_drain);

    parameter IDLE  = 3'b111,
              FILL  = 3'b000,
              WASH  = 3'b001,
              RINSE = 3'b010,
              SPIN  = 3'b011,
              STOP  = 3'b100,
              TIMER = 4'd10,
              VALVE_DURATION = 2'd2;


    reg [2:0] prev_state;
    reg [3:0] count;
    reg running;
    reg paused;
    reg times = 1'b0;
    reg lidcond;
    reg pauser;

    always @(posedge clk or posedge reset) begin
        if(done & !lid)
            stage <= IDLE;
        if(reset) begin
            count <= 2'b00;
            case (stage)
                WASH : begin
                    if(input_valve == 1'b1) begin
                        input_valve <= 1'b0;
                        if(count < VALVE_DURATION) begin
                                output_drain <= 1'b1;
                                count++;
                        end
                        else begin
                                output_drain <= 1'b0;
                                count <= 2'b00;
                        end
                    end
                    else begin
                        input_valve <= 1'b0;
                        output_drain <= 1'b0;
                    end
                end
                RINSE : begin
                    if(input_valve == 1'b1 || output_drain == 1'b1) begin
                        input_valve <= 1'b0;
                        if(count < VALVE_DURATION) begin
                                output_drain <= 1'b1;
                                count++;
                        end
                        else begin
                                output_drain <= 1'b0;
                                count <= 2'b00;
                        end
                    end
                end
                SPIN : begin
                    if(output_drain == 1'b1) begin
                        if(count < VALVE_DURATION) begin
                                output_drain <= 1'b1;
                                count++;
                        end
                        else begin
                                output_drain <= 1'b0;
                                count <= 2'b00;
                        end
                    end
                end
                default : begin
                    input_valve <= 1'b0;
                    output_drain <= 1'b0;
                end
            endcase
            stage <= IDLE;
            prev_state <= IDLE;
            running <= 1'b0;
            paused <= 1'b0;
            done <= 1'b0; 
        end
        else begin
            if(pause) begin
                running <= 1'b0;
                if(stage != IDLE) 
                    prev_state <= stage;
                stage <= IDLE;
                paused <= 1'b1;
                input_valve <= 1'b0;
                output_drain <= 1'b0;
            end
            else if(pauser) begin
                running <= 1'b0;
                if(stage != IDLE) 
                    prev_state <= stage;
                stage <= IDLE;
                input_valve <= 1'b0;
                output_drain <= 1'b0;
                if(prev_state == FILL && lid) begin
                    lidcond <= 1'b1;
                    pauser <= 1'b0;
                    times <= 1'b1;
                end
                else if((prev_state == WASH || prev_state == RINSE || prev_state == SPIN) && !lid) begin
                    lidcond <= 1'b1;
                    pauser <= 1'b0;
                end
            end

            else if(start || ((running || paused || lidcond)) && !done) begin
                running <= 1'b1;
                if(paused || lidcond) begin
                    stage <= prev_state;
                    paused <= 1'b0;
                    lidcond <= 1'b0;
                end

                case (stage)
                    FILL: begin
                        input_valve <= 1'b0;
                        output_drain <= 1'b0;
                        if(lid && !times)
                            pauser <= 1'b1;
                    end
                    WASH: begin
                        if(lid) begin
                            pauser <= 1'b1;
                        end
                        else begin
                            output_drain <= 1'b0;
                            if(count < VALVE_DURATION)
                                input_valve <= 1'b1;
                            else
                                input_valve <= 1'b0;  
                        end     
                    end
                    RINSE: begin
                        if(lid) begin
                            pauser <= 1'b1;
                        end
                        else begin
                            case (count) 
                                4'd0: begin input_valve <= 1'b0 ; output_drain <= 1'b1; end
                                4'd2: begin input_valve <= 1'b1 ; output_drain <= 1'b0; end
                                4'd4: begin input_valve <= 1'b0 ; output_drain <= 1'b1; end
                                4'd6: begin input_valve <= 1'b1 ; output_drain <= 1'b0; end
                                4'd8: begin input_valve <= 1'b0 ; output_drain <= 1'b1; end
                                4'd10:begin input_valve <= 1'b0 ; output_drain <= 1'b1; end
                            endcase
                        end
                    end
                    SPIN: begin
                        if(lid) begin
                            pauser <= 1'b1;
                        end
                        else begin
                            input_valve <= 1'b0;
                            if(count < VALVE_DURATION)
                                output_drain <= 1'b1;
                            else
                                output_drain <= 1'b0;
                        end
                    end
                    STOP : begin
                        input_valve <= 1'b0;
                        output_drain <= 1'b0;
                    end
                endcase                
                if(count < TIMER) begin
                    count <= count + 1;
                end
                else begin
                    if (stage == STOP) begin
                        done <= 1'b1;
                        running <= 1'b0;
                        stage <= IDLE;
                        count <= 2'b00;
                    end
                    else if(stage == FILL) begin
                        if(!lid) begin
                            stage <= stage + 1;
                            count <= 2'b00;
                        end
                    end
                    else begin
                        stage <= stage + 1;
                        done <= 1'b0;
                        count <= 2'b00;
                    end
                end
            end 
        end
    end
endmodule

tb.v
`include "design.v"

module AWMC_tb();
    reg clk, reset, start, pause,lid;
    wire [2:0] stage;
    wire done;
    wire lido;

    AWMC uut(.clk(clk),.reset(reset),.start(start),.pause(pause),.stage(stage),.done(done),.lid(lid));

    initial begin
        reset = 1'b0;
        #1
        reset = 1'b1;
        #1
        reset = 1'b0;
        clk = 1'b0;

        forever #5 clk = ~clk;
    end

    initial begin
        start = 1'b0;
        pause = 1'b0;

        $dumpfile("tb.vcd");
        $dumpvars(0,AWMC_tb);

        #10
        start = 1'b1;
        lid = 1'b1;
        #20
        start = 1'b0;
        #100
        pause = 1'b1;
        lid = 1'b0;
        #105
        pause = 1'b0;
        #110
        start = 1'b1;
        #120 
        start = 1'b0;
        #150
        reset = 1'b0;
        #155
        start = 1'b1;
        lid = 1'b1;
        #160
        start = 1'b0;
        #165
        lid = 1'b1;
        #167
        lid = 1'b0;
        #170
        pause = 1'b0;
        #200
        reset = 1'b1;
        start = 1'b1;
        lid = 1'b1;
        #205
        reset = 1'b0;  
        #240
        start = 1'b0;
        lid = 1'b0;
        #250
        pause = 1'b1;
        #310
        pause = 1'b0;
        lid = 1'b1;
        #360
        lid = 1'b0;

        #400 $finish;

    end

endmodule

tb.vcd
$date
	Mon Aug  4 15:40:55 2025
$end
$version
	Icarus Verilog
$end
$timescale
	1s
$end
$scope module AWMC_tb $end
$var wire 3 ! stage [2:0] $end
$var wire 1 " done $end
$var reg 1 # clk $end
$var reg 1 $ lid $end
$var reg 1 % pause $end
$var reg 1 & reset $end
$var reg 1 ' start $end
$scope module uut $end
$var wire 1 # clk $end
$var wire 1 $ lid $end
$var wire 1 % pause $end
$var wire 1 & reset $end
$var wire 1 ' start $end
$var reg 4 ( count [3:0] $end
$var reg 1 " done $end
$var reg 1 ) input_valve $end
$var reg 1 * lidcond $end
$var reg 1 + output_drain $end
$var reg 1 , paused $end
$var reg 1 - pauser $end
$var reg 3 . prev_state [2:0] $end
$var reg 1 / running $end
$var reg 3 0 stage [2:0] $end
$var reg 1 1 times $end
$upscope $end
$upscope $end
$enddefinitions $end
#0
$dumpvars
01
bx 0
x/
bx .
x-
x,
x+
x*
x)
bx (
0'
0&
0%
x$
x#
x"
bx !
$end
#1
0"
0,
0/
b111 .
b111 !
b111 0
0+
0)
b0 (
1&
#2
0#
0&
#7
1#
#10
1$
1'
#12
0#
#17
b1 (
1/
1#
#22
0#
#27
b10 (
1#
#30
0'
#32
0#
#37
b11 (
1#
#42
0#
#47
b100 (
1#
#52
0#
#57
b101 (
1#
#62
0#
#67
b110 (
1#
#72
0#
#77
b111 (
1#
#82
0#
#87
b1000 (
1#
#92
0#
#97
b1001 (
1#
#102
0#
#107
b1010 (
1#
#112
0#
#117
b0 (
b0 !
b0 0
1#
#122
0#
#127
b1 (
1-
1#
#130
0$
1%
#132
0#
#137
1,
b111 !
b111 0
b0 .
0/
1#
#142
0#
#147
1#
#152
0#
#157
1#
#162
0#
#167
1#
#172
0#
#177
1#
#182
0#
#187
1#
#192
0#
#197
1#
#202
0#
#207
1#
#212
0#
#217
1#
#222
0#
#227
1#
#232
0#
#235
0%
#237
1#
#242
0#
#247
1#
#252
0#
#257
1#
#262
0#
#267
1#
#272
0#
#277
1#
#282
0#
#287
1#
#292
0#
#297
1#
#302
0#
#307
1#
#312
0#
#317
1#
#322
0#
#327
1#
#332
0#
#337
1#
#342
0#
#345
1'
#347
1#
#352
0#
#357
1#
#362
0#
#367
1#
#372
0#
#377
1#
#382
0#
#387
1#
#392
0#
#397
1#
#402
0#
#407
1#
#412
0#
#417
1#
#422
0#
#427
1#
#432
0#
#437
1#
#442
0#
#447
1#
#452
0#
#457
1#
#462
0#
#465
0'
